image_grid/__init__.py
image_grid-0.0.4.data/scripts/image-grid
image_grid-0.0.4.dist-info/METADATA
image_grid-0.0.4.dist-info/WHEEL
image_grid-0.0.4.dist-info/top_level.txt
image_grid-0.0.4.dist-info/RECORD
