Metadata-Version: 2.1
Name: image-grid
Version: 0.0.4
Summary: assembles images in a grid
Home-page: https://github.com/RasmusHaugaard/image-grid
Author: Rasmus Laurvig Haugaard
Author-email: rasmus.l.haugaard@gmail.com
License: UNKNOWN
Platform: UNKNOWN
Requires-Python: >=3.6
Requires-Dist: numpy
Requires-Dist: Pillow
Requires-Dist: natsort
